README.md
setup.py
consumer_api/__init__.py
consumer_api/consumer_api.py
consumer_api_telegram_bot.egg-info/PKG-INFO
consumer_api_telegram_bot.egg-info/SOURCES.txt
consumer_api_telegram_bot.egg-info/dependency_links.txt
consumer_api_telegram_bot.egg-info/requires.txt
consumer_api_telegram_bot.egg-info/top_level.txt