Metadata-Version: 2.1
Name: consumer-api-telegram-bot
Version: 0.0.2
Summary: Implementacao da api de um bot para telegram
Home-page: UNKNOWN
Author: Lucas Alves
Author-email: lucasal072@gmail.com
License: MIT License
Keywords: consumer_api_lucas
Platform: UNKNOWN
